{"cameraMode":{"drawMode":0,"name":"Shaded","section":"Shading Mode"},"sceneLighting":true,"audioPlay":false,"sceneViewState":{"showFog":true,"showMaterialUpdate":false,"showSkybox":true,"showFlares":true,"showImageEffects":true,"showParticleSystems":true},"in2DMode":false,"pivot":{"x":-0.2524421513080597,"y":-1.6586713790893555,"z":7.425757884979248},"rotation":{"x":0.4219512939453125,"y":0.03262665867805481,"z":-0.015196800231933594,"w":0.9059045314788818},"size":9.386799812316895,"orthographic":false}